falcon_policy/__init__.py
falcon_policy/config.py
falcon_policy/middleware.py
falcon_policy/policy.py
falcon_policy-0.2.0.dist-info/LICENSE
falcon_policy-0.2.0.dist-info/METADATA
falcon_policy-0.2.0.dist-info/WHEEL
falcon_policy-0.2.0.dist-info/entry_points.txt
falcon_policy-0.2.0.dist-info/top_level.txt
falcon_policy-0.2.0.dist-info/RECORD
