Metadata-Version: 2.1
Name: falcon-policy
Version: 0.2.0
Summary: Policy middleware for Falcon APIs
Home-page: https://github.com/falconry/falcon-policy
Author: John Vrbanac
Author-email: john.vrbanac@linux.com
License: Apache v2
Keywords: falcon middleware policy rbac role based access
Platform: UNKNOWN
Classifier: Development Status :: 3 - Alpha
Classifier: Intended Audience :: Developers
Classifier: License :: OSI Approved :: Apache Software License
Classifier: Programming Language :: Python :: 2.7
Classifier: Programming Language :: Python :: 3.4
Classifier: Programming Language :: Python :: 3.5
Classifier: Programming Language :: Python :: 3.6
Requires-Dist: falcon
Requires-Dist: six
